odoo/addons/beesdoo_worker_status/README.rst
odoo/addons/beesdoo_worker_status/__init__.py
odoo/addons/beesdoo_worker_status/__manifest__.py
odoo/addons/beesdoo_worker_status/demo/tasks.xml
odoo/addons/beesdoo_worker_status/i18n/beesdoo_worker_status.pot
odoo/addons/beesdoo_worker_status/models/__init__.py
odoo/addons/beesdoo_worker_status/models/cooperative_status.py
odoo/addons/beesdoo_worker_status/models/task.py
odoo/addons/beesdoo_worker_status/readme/CONTRIBUTORS.rst
odoo/addons/beesdoo_worker_status/readme/DESCRIPTION.rst
odoo/addons/beesdoo_worker_status/static/description/index.html
odoo/addons/beesdoo_worker_status/tests/__init__.py
odoo/addons/beesdoo_worker_status/tests/test_beesdoo_shift.py
odoo12_addon_beesdoo_worker_status-12.0.1.0.0.99.dev32.dist-info/METADATA
odoo12_addon_beesdoo_worker_status-12.0.1.0.0.99.dev32.dist-info/WHEEL
odoo12_addon_beesdoo_worker_status-12.0.1.0.0.99.dev32.dist-info/top_level.txt
odoo12_addon_beesdoo_worker_status-12.0.1.0.0.99.dev32.dist-info/RECORD
