Metadata-Version: 2.1
Name: odoo12-addon-beesdoo-worker-status
Version: 12.0.1.0.0.99.dev32
Summary: Worker status management specific to beescoop.
Home-page: https://github.com/beescoop/Obeesdoo
Author: Thibault Francois, Elouan Le Bars, Coop IT Easy SCRLfs
License: AGPL-3
Platform: UNKNOWN
Classifier: Programming Language :: Python
Classifier: Framework :: Odoo
Classifier: Framework :: Odoo :: 12.0
Classifier: License :: OSI Approved :: GNU Affero General Public License v3
Requires-Python: >=3.5
Requires-Dist: odoo12-addon-beesdoo-base
Requires-Dist: odoo12-addon-beesdoo-shift
Requires-Dist: odoo (<12.1dev,>=12.0a)
